pycodechef/__init__.py
pycodechef/client.py
pycodechef-0.0.2.dist-info/METADATA
pycodechef-0.0.2.dist-info/RECORD
pycodechef-0.0.2.dist-info/WHEEL
pycodechef-0.0.2.dist-info/top_level.txt
