Metadata-Version: 2.1
Name: pycodechef
Version: 0.0.2
Summary: Python Wrapper fo Codechef REST API
Home-page: https://github.com/appi147/pycodechef
Author: Arpit Choudhary
Author-email: arpitkumar147@gmail.com
License: MIT License
Requires-Dist: requests
